pytglib/__init__.py
pytglib/_pytglib.cpython-311-x86_64-linux-gnu.so
temporalgraphlib.libs/libgomp-870cb1d0.so.1.0.0
temporalgraphlib-1.7.0.dist-info/METADATA
temporalgraphlib-1.7.0.dist-info/WHEEL
temporalgraphlib-1.7.0.dist-info/RECORD
temporalgraphlib-1.7.0.dist-info/licenses/LICENSE.md
