Metadata-Version: 2.2
Name: temporalgraphlib
Version: 1.7.0
License: Copyright (c) 2022 Lutz Oettershagen
Classifier: Programming Language :: Python :: 3
Classifier: License :: OSI Approved :: MIT License
Classifier: Operating System :: OS Independent
Classifier: Intended Audience :: Science/Research
Classifier: Programming Language :: C++
Requires-Python: >=3.8
